G_Bdistribution-1.dist-info/DESCRIPTION.rst
G_Bdistribution-1.dist-info/METADATA
G_Bdistribution-1.dist-info/RECORD
G_Bdistribution-1.dist-info/WHEEL
G_Bdistribution-1.dist-info/metadata.json
G_Bdistribution-1.dist-info/top_level.txt
distributions/Binomialdistribution.py
distributions/Gaussiandistribution.py
distributions/Generaldistribution.py
distributions/__init__.py
