Metadata-Version: 2.0
Name: G-Bdistribution
Version: 1
Summary: Gaussian and Binomial distributions
Home-page: UNKNOWN
Author: Ravineel Singhi
Author-email: rajatsinghi89@gmail.com
License: UNKNOWN
Platform: UNKNOWN
